[
  {
    "quote": "Не чекай ідеального моменту. Створи його.",
    "action": "Запиши одну справу, яку відкладаєш, і зроби перший крок протягом 10 хвилин."
  },
  {
    "quote": "Щоденні дії = великі зміни.",
    "action": "Виділи 15 хвилин на одну важливу задачу без телефону (режим фокус)."
  },
  {
    "quote": "Ти — той, ким вирішуєш бути.",
    "action": "Одним реченням сформулюй, ким хочеш бути через рік. Збережи це як нагадування."
  },
  {
    "quote": "Прогрес, а не перфекціонізм.",
    "action": "Зроби швидку міні-версію завдання на 20% — без ідеальності."
  },
  {
    "quote": "Дисципліна — це любов до себе у майбутньому.",
    "action": "Зроби щось корисне для свого завтрашнього «я»: підготуй одяг/робоче місце/план."
  },
  {
    "quote": "Енергія приходить під час руху.",
    "action": "3 хвилини активності: присідання/планка/прогулянка. Потім повернись до справ."
  },
  {
    "quote": "Ти можеш більше, ніж думаєш. Просто почни.",
    "action": "Вибери одну мікродію на 5 хвилин і зроби її прямо зараз."
  }
]